PomeloRDG/Const.py
PomeloRDG/Graph.py
PomeloRDG/IO.py
PomeloRDG/Maths.py
PomeloRDG/String.py
PomeloRDG/Utils.py
PomeloRDG/Vector.py
PomeloRDG/__init__.py
PomeloRDG-0.0.9.dist-info/LICENSE
PomeloRDG-0.0.9.dist-info/METADATA
PomeloRDG-0.0.9.dist-info/WHEEL
PomeloRDG-0.0.9.dist-info/top_level.txt
PomeloRDG-0.0.9.dist-info/RECORD
